ad_ci_tools/__init__.py
ad_ci_tools/utils.py
ad_ci_tools-0.1.9.dist-info/METADATA
ad_ci_tools-0.1.9.dist-info/WHEEL
ad_ci_tools-0.1.9.dist-info/top_level.txt
ad_ci_tools-0.1.9.dist-info/RECORD
