Metadata-Version: 2.1
Name: ad-ci-tools
Version: 0.1.9
Summary: Ci library with miscellaneous utils
Home-page: https://github.com/arenadata/ci_tools
Author: Rotaru Sergey
Author-email: rsv@arenadata.io
License: UNKNOWN
Platform: UNKNOWN
Classifier: Programming Language :: Python :: 3
Classifier: License :: OSI Approved :: Apache Software License
Classifier: Operating System :: OS Independent
Requires-Python: >=3.6
Requires-Dist: gitpython
Requires-Dist: wheel
